Metadata-Version: 1.0
Name: distributions-sarish
Version: 0.1
Summary: Gaussian and Binomial distributions
Home-page: UNKNOWN
Author: Sarish Biswas
Author-email: sarishbiswas@gmail.com
License: UNKNOWN
Platform: UNKNOWN
